{
  "cate": "5",
  "date": "5æ25æ¥ 22æ34å",
  "datetime": "2018-05-25T22:34",
  "video": "/news/html/20180525/movie/k10011453331_201805260643_201805260721.html",
  "duration": 56,
  "img": "html/20180525/K10011453331_1805252249_1805252249_01_02.jpg",
  "title": "仮想通貨で収入１億円以上は331人 国税庁",
  "summary": "去年分の所得の確定申告をした人のうち、去年１年間に価格が急騰した仮想通貨の取引によって１億円以上の収入があったと見られる人が３００人以上いたことが国税庁のまとめでわかりました。",
  "more": "国税庁によりますと、去年分の所得税を納めるため確定申告をした個人事業主やサラリーマンは６４０万人で、所得税の総額は前の年よりも４.６％多い３兆２０３７億円でした。<br /><br />また、去年１年間にビットコインをはじめとする仮想通貨の価格が高騰したことを反映して、仮想通貨の取引によって１億円以上の収入があったと見られる人が少なくとも３３１人に上りました。<br /><br />日本仮想通貨交換業協会によりますと、国内の主な交換業者には仮想通貨の取引を目的にした口座が３５０万あり、ことし３月末の時点で仮想通貨の時価が１億円以上の口座は２６８あったということです。<br /><br />国税庁は「仮想通貨の取引に伴う所得はおおむね適正に申告されたのではないか」としています。",
  "body": [
    {
      "title": "「億り人」はごく一部",
      "img": "",
      "align": "",
      "text": "仮想通貨の取引で１億円以上の収入があったと見られる人が３００人を超えたことについて、仮想通貨に詳しい麗澤大学の中島真志教授は「１億円以上の利益が出た人は『億り人』ともてはやされたが、仮想通貨に投資しているのは２００万人から３００万人いるとされているので、ごく一部だ。去年、ブームが始まる前に多額の仮想通貨を買い、上昇局面で売り抜けた人に限られるということだろう」と話しています。",
      "textPos": ""
    }
  ],
  "relationNews": [],
  "relationLink": [],
  "word": [
    {
      "link": "word/0000481.html",
      "title": "仮想通貨"
    }
  ],
  "news_id": "k10011453331000",
  "yyyy": "2018",
  "mm": "05",
  "dd": "25",
  "url": "https://www3.nhk.or.jp/news/html/20180525/k10011453331000.html"
}