{
  "reikai": {
    "entries": {
      "0000": [
        {
          "def": "<ruby><rb>先頭</rb><rt>せんとう</rt></ruby>。<ruby><rb>真</rb><rt>ま</rt></ruby>っ<ruby><rb>先</rb><rt>さき</rt></ruby>。<ruby><rb>一番</rb><rt>いちばん</rt></ruby>。",
          "hyouki": [
            "トップ"
          ]
        }
      ],
      "0001": [
        {
          "def": "<ruby><rb>共和国</rb><rt>きょうわこく</rt></ruby>で、その<ruby><rb>国</rb><rt>くに</rt></ruby>を<ruby><rb>代表</rb><rt>だいひょう</rt></ruby>する<ruby><rb>人</rb><rt>ひと</rt></ruby>。",
          "hyouki": [
            "大統領"
          ]
        }
      ],
      "0002": [
        {
          "def": "おだやかで、<ruby><rb>無事</rb><rt>ぶじ</rt></ruby>なこと。",
          "hyouki": [
            "平和"
          ]
        },
        {
          "def": "<ruby><rb>戦争</rb><rt>せんそう</rt></ruby>がなく、<ruby><rb>世</rb><rt>よ</rt></ruby>の<ruby><rb>中</rb><rt>なか</rt></ruby>が<ruby><rb>無事</rb><rt>ぶじ</rt></ruby>に<ruby><rb>治</rb><rt>おさ</rt></ruby>まっていること。",
          "hyouki": [
            "平和"
          ]
        }
      ],
      "0003": [
        {
          "def": "<ruby><rb>核分裂</rb><rt>かくぶんれつ</rt></ruby>や<ruby><rb>核融合</rb><rt>かくゆうごう</rt></ruby>によって<ruby><rb>出</rb><rt>で</rt></ruby>るエネルギーを<ruby><rb>利用</rb><rt>りよう</rt></ruby>した<ruby><rb>兵器</rb><rt>へいき</rt></ruby>。<ruby><rb>原子爆弾</rb><rt>げんしばくだん</rt></ruby>や、<ruby><rb>水素爆弾</rb><rt>すいそばくだん</rt></ruby>など。",
          "hyouki": [
            "核兵器"
          ]
        }
      ]
    }
  }
}
